mikesh/__init__.py
mikesh/spectrum.py
mikesh/spectrum_methods/_constructor.py
mikesh/spectrum_methods/_equal.py
mikesh/spectrum_methods/_export.py
mikesh/spectrum_methods/_groups.py
mikesh/spectrum_methods/_integral.py
mikesh/spectrum_methods/_integrity.py
mikesh/spectrum_methods/_regroup.py
mikesh-0.0.1.dist-info/LICENSE
mikesh-0.0.1.dist-info/METADATA
mikesh-0.0.1.dist-info/WHEEL
mikesh-0.0.1.dist-info/top_level.txt
mikesh-0.0.1.dist-info/RECORD
