Metadata-Version: 2.1
Name: mikesh
Version: 0.0.1
Summary: Package for working with neutron spectra.
Author-email: Mikesh Foundation <author@example.com>
Project-URL: Homepage, https://github.com/Mikesh-Foundation/mikesh
Project-URL: Bug Tracker, https://github.com/Mikesh-Foundation/mikesh/issues
Classifier: Programming Language :: Python :: 3
Classifier: License :: OSI Approved :: MIT License
Classifier: Operating System :: OS Independent
Classifier: Intended Audience :: Science/Research
Classifier: Topic :: Scientific/Engineering :: Physics
Requires-Python: >=3.7
License-File: LICENSE
